cimulator/__init__.py
cimulator/cli.py
cimulator/config.py
cimulator/job_expander.py
cimulator/loader.py
cimulator/simulation_engine.py
cimulator/types.py
cimulator/validator.py
cimulator/variable_expander.py
cimulator/workflow.py
cimulator-0.1.2.dist-info/LICENSE
cimulator-0.1.2.dist-info/METADATA
cimulator-0.1.2.dist-info/WHEEL
cimulator-0.1.2.dist-info/entry_points.txt
cimulator-0.1.2.dist-info/RECORD
