Metadata-Version: 2.3
Name: cimulator
Version: 0.1.2
Summary: A tool to validate and simulate GitLab CI pipelines
License: MIT
Keywords: gitlab,ci,pipeline,simulation,validation
Author: Ilia Barkov
Author-email: barkovian@gmail.com
Requires-Python: >=3.10
Classifier: Development Status :: 4 - Beta
Classifier: Intended Audience :: Developers
Classifier: Intended Audience :: System Administrators
Classifier: License :: OSI Approved :: MIT License
Classifier: Programming Language :: Python :: 3
Classifier: Programming Language :: Python :: 3.10
Classifier: Programming Language :: Python :: 3.11
Classifier: Topic :: Software Development :: Build Tools
Classifier: Topic :: Software Development :: Testing
Requires-Dist: iniconfig (>=2.1.0)
Requires-Dist: packaging (>=24.2)
Requires-Dist: pluggy (>=1.5.0)
Requires-Dist: pyyaml (>=6.0.2)
Requires-Dist: setuptools (>=78.1.0)
Project-URL: Repository, https://github.com/Zvord/cimulator
